{
    "AUD": { "symbol": "$", "multiplier": 0.76, "limit": 1000, "decimals": 2 },
    "BRL": { "symbol": "$", "multiplier": 0.27, "limit": 1000, "decimals": 2 },
    "CAD": { "symbol": "$", "multiplier": 0.77, "limit": 1000, "decimals": 2 },
    "CHF": { "symbol": "₣", "multiplier": 1.0, "limit": 1000, "decimals": 2 },
    "CZK": { "symbol": "$", "multiplier": 0.041, "limit": 1000, "decimals": 2 },
    "DKK": { "symbol": "$", "multiplier": 0.15, "limit": 1000, "decimals": 2 },
    "EUR": { "symbol": "€", "multiplier": 1.1, "limit": 1000, "decimals": 2 },
    "GBP": { "symbol": "£", "multiplier": 1.4, "limit": 1000, "decimals": 2 },
    "HKD": { "symbol": "$", "multiplier": 0.13, "limit": 1000, "decimals": 2 },
    "HUF": { "symbol": "$", "multiplier": 0.0036, "limit": 1000, "decimals": 2 },
    "ILS": { "symbol": "$", "multiplier": 0.26, "limit": 1000, "decimals": 2 },
    "JPY": { "symbol": "¥", "multiplier": 0.0090, "limit": 100000, "decimals": 0 },
    "MXN": { "symbol": "$", "multiplier": 0.057, "limit": 1000, "decimals": 2 },
    "MYR": { "symbol": "$", "multiplier": 0.25, "limit": 1000, "decimals": 2 },
    "NOK": { "symbol": "$", "multiplier": 0.12, "limit": 1000, "decimals": 2 },
    "NZD": { "symbol": "$", "multiplier": 0.68, "limit": 1000, "decimals": 2 },
    "PHP": { "symbol": "₱", "multiplier": 0.022, "limit": 1000, "decimals": 2 },
    "PLN": { "symbol": "$", "multiplier": 0.26, "limit": 1000, "decimals": 2 },
    "SEK": { "symbol": "$", "multiplier": 0.12, "limit": 1000, "decimals": 2 },
    "SGD": { "symbol": "$", "multiplier": 0.74, "limit": 1000, "decimals": 2 },
    "THB": { "symbol": "$", "multiplier": 0.029, "limit": 1000, "decimals": 2 },
    "TWD": { "symbol": "$", "multiplier": 0.031, "limit": 1000, "decimals": 2 },
    "USD": { "symbol": "$", "multiplier": 1.0, "limit": 1000, "decimals": 2 }
}
