{
    "ad": "And\u00f2rra",
    "ae": "Emirats Arabis Units",
    "af": "Afganistan",
    "ag": "Antigua e Barbuda",
    "ai": "Anguilla",
    "al": "Albania",
    "am": "Armenia",
    "ao": "Ang\u00f2la",
    "aq": "Antarctica",
    "ar": "Argentina",
    "as": "Samoa american",
    "at": "\u00c0ustria",
    "au": "Austr\u00e0lia",
    "aw": "Aruba",
    "az": "Azerbaitjan",
    "ba": "B\u00f2snia e Ercegovina",
    "bb": "Barbados",
    "bd": "Banglad\u00e8sh",
    "be": "Belgica",
    "bf": "Burkina Faso",
    "bg": "Bulgaria",
    "bh": "Bahrayn",
    "bi": "Burundi",
    "bj": "Benin",
    "bl": "Sant Bertomieu",
    "bm": "Bermuda",
    "bn": "Brunei",
    "bo": "Bol\u00edvia",
    "bq": "Antilhas neerlandesas",
    "br": "Brasil",
    "bs": "Bahamas, Las",
    "bt": "Botan",
    "bv": "Illa Bouvet",
    "bw": "Botswana",
    "by": "Bielorussia",
    "bz": "Belize",
    "ca": "Canad\u00e0",
    "cc": "Illas Cocos (Keeling)",
    "cd": "C\u00f2ngo (Kinshasa)",
    "cf": "Republica Centrafricana",
    "cg": "C\u00f2ngo (Brazzaville)",
    "ch": "So\u00efssa",
    "ci": "C\u00f2sta d'Ev\u00f2ri",
    "ck": "Illas Cook",
    "cl": "Chile",
    "cm": "Cameron",
    "cn": "China",
    "co": "Col\u00f3mbia",
    "cp": "Illa Clipperton",
    "cr": "C\u00f2sta Rica",
    "cu": "Cuba",
    "cv": "Cap Verd",
    "cw": "Cura\u00e7ao",
    "cx": "Illa Christmas",
    "cy": "Chipre",
    "cz": "Republica ch\u00e8ca",
    "de": "Alemanha",
    "dg": "Diego Garcia",
    "dj": "Jiboti",
    "dk": "Danemarc",
    "dm": "Dominica",
    "do": "Republica Dominicana",
    "dz": "Argeria",
    "ec": "Eq\u00fcator",
    "ee": "Est\u00f2nia",
    "eg": "Egipte",
    "eh": "Sahara occidental",
    "er": "Eritr\u00e8a",
    "es": "Espanha",
    "et": "Etiopia",
    "fi": "Finl\u00e0ndia",
    "fj": "Fiji",
    "fk": "Illas Falkland (Illas Malvinas)",
    "fm": "Micronesia, Estats Federats de",
    "fo": "Illas Fer\u00f2e",
    "fr": "Fran\u00e7a",
    "ga": "Gabon",
    "gb": "Reialme unit",
    "gd": "Grenada",
    "ge": "Georgia",
    "gf": "Guiana francesa",
    "gg": "Guernsey",
    "gh": "Ghana",
    "gi": "Gibraltar",
    "gl": "Groenland",
    "gm": "G\u00e0mbia",
    "gn": "Guin\u00e8a",
    "gp": "Guadalope",
    "gq": "Guin\u00e8a Eq\u00fcatoriala",
    "gr": "Gr\u00e8cia",
    "gs": "Georgia del Sud e Sud de las illas Sandwich",
    "gt": "Guatemala",
    "gu": "Guam",
    "gw": "Guin\u00e8a Bissau",
    "gy": "Guyana",
    "hk": "Hong Kong",
    "hm": "Illa Heard e illas McDonald",
    "hn": "Honduras",
    "hr": "Cro\u00e0cia",
    "ht": "Hait\u00ed",
    "hu": "Ongria",
    "id": "Indonesia",
    "ie": "Irlanda",
    "il": "Isra\u00e8l",
    "im": "Illa de Man",
    "in": "\u00cdndia",
    "io": "Ocean Indian, territ\u00f2ri britanic de l'illa de l'",
    "iq": "Iraq",
    "ir": "Iran",
    "is": "Isl\u00e0ndia",
    "it": "It\u00e0lia",
    "je": "Jersey",
    "jm": "Jamaica",
    "jo": "Jordania",
    "jp": "Japon",
    "ke": "Kenya",
    "kg": "Quirguizstan",
    "kh": "Camb\u00f2tja",
    "ki": "Kiribati",
    "km": "Com\u00f2ras",
    "kn": "Sant Kitts e Nevis",
    "kp": "Cor\u00e8a del N\u00f2rd",
    "kr": "Cor\u00e8a del Sud",
    "kw": "Kowait",
    "ky": "Illas Cayman",
    "kz": "Cazacstan",
    "la": "Laos",
    "lb": "Liban",
    "lc": "Santa L\u00facia",
    "li": "Liechtenstein",
    "lk": "Sri Lanka",
    "lr": "Lib\u00e8ria",
    "ls": "Lesotho",
    "lt": "Litu\u00e0nia",
    "lu": "Luxemborg",
    "lv": "Let\u00f2nia",
    "ly": "Libia",
    "ma": "Marr\u00f2c",
    "mc": "M\u00f3negue",
    "md": "Mold\u00e0via",
    "me": "Montenegro",
    "mf": "Sant Martin",
    "mg": "Madagascar",
    "mh": "Illas Marshall",
    "mk": "Maced\u00f2nia del N\u00f2rd",
    "ml": "Mali",
    "mm": "Burma",
    "mn": "Mongolia",
    "mo": "Macau",
    "mp": "Illas Mariana del N\u00f2rd",
    "mq": "Martinica",
    "mr": "Maurit\u00e0nia",
    "ms": "Montserrat",
    "mt": "Malta",
    "mu": "Maurici",
    "mv": "Maldivas",
    "mw": "Malawi",
    "mx": "Mexic",
    "my": "Mal\u00e0isia",
    "mz": "Mo\u00e7ambic",
    "na": "Namibia",
    "nc": "N\u00f2va Caled\u00f2nia",
    "ne": "Nig\u00e8r",
    "nf": "Illa Norfolk",
    "ng": "Nig\u00e8ria",
    "ni": "Nicaragua",
    "nl": "Pa\u00efses Basses",
    "no": "Norv\u00e8gia",
    "np": "Nepal",
    "nr": "Nauru",
    "nu": "Niue",
    "nz": "N\u00f2va Zelanda",
    "om": "Oman",
    "pa": "Panam\u00e0",
    "pe": "Per\u00f3",
    "pf": "Polinesia francesa",
    "pg": "Papoa-N\u00f2va Guin\u00e8a",
    "ph": "Filipinas",
    "pk": "Paquistan",
    "pl": "Polonha",
    "pm": "Sant P\u00e8ire e Miquelon",
    "pn": "Illas Pitcairn",
    "pr": "Puerto Rico",
    "pt": "Portugal",
    "pw": "Palau",
    "py": "Paraguai",
    "qa": "Qatar",
    "qm": "Illas Midway",
    "qs": "Bassas da India",
    "qu": "Illa Juan de Nova",
    "qw": "Illas Wake",
    "qx": "Illas Glorioso",
    "qz": "Akrotiri",
    "re": "Re\u00fcnion",
    "ro": "Romania",
    "rs": "S\u00e8rbia",
    "ru": "Russia",
    "rw": "Rwanda",
    "sa": "Arabia Saudita",
    "sb": "Illas Solomon",
    "sc": "Seich\u00e8las",
    "sd": "Sodan",
    "se": "Su\u00e8cia",
    "sg": "Singapor",
    "sh": "Santa Helena, Ascension e Tristan da Cunha",
    "si": "Eslov\u00e8nia",
    "sk": "Eslovaquia",
    "sl": "Sierra Leone",
    "sm": "Sant Marin",
    "sn": "Senegal",
    "so": "Somalia",
    "sr": "Surinam",
    "ss": "Sodan del Sud",
    "st": "S\u00e3o Tom\u00e9 e Pr\u00edncipe",
    "sv": "Salvador",
    "sx": "Sant Martin",
    "sy": "Siria",
    "sz": "Eswatini",
    "tc": "Illas Turks e Caicos",
    "td": "Chad",
    "tf": "T\u00e8rras Australas e Antarticas Francesas",
    "tg": "T\u00f2go",
    "th": "Tail\u00e0ndia",
    "tj": "Tatgiquistan",
    "tk": "Tokelau",
    "tl": "Tim\u00f2r \u00c8st",
    "tm": "Turcmenistan",
    "tn": "Tunisia",
    "to": "T\u00f2nga",
    "tr": "Turquia",
    "tt": "Trinitat e Tobago",
    "tv": "Tuvalu",
    "tw": "Taiwan",
    "tz": "Tanzania",
    "ua": "Ucra\u00efna",
    "ug": "Oganda",
    "us": "Estats Units",
    "uy": "Uruguai",
    "uz": "Ozbequistan",
    "va": "Vatican",
    "vc": "Sant Vincen\u00e7 e las Grenadinas",
    "ve": "Vene\u00e7u\u00e8la",
    "vg": "Illas Verges britanicas",
    "vi": "Illas Verges n\u00f2rd-americanas",
    "vn": "Vietnam",
    "vu": "Vanuatu",
    "wf": "Wallis e Futuna",
    "ws": "Samoa",
    "xa": "Illas Ashmore e Cartier",
    "xb": "Illa Baker",
    "xc": "Illas de la Mar de Coral",
    "xd": "Dhekelia",
    "xe": "Illa Eur\u00f2pa",
    "xg": "Franja de Gaza",
    "xh": "Illa Howland",
    "xj": "Jan Mayen",
    "xk": "Kosova",
    "xl": "At\u00f2l Palmyra",
    "xm": "Escu\u00e8l Kingman",
    "xp": "Illas Paracel",
    "xq": "Illa Jarvis",
    "xr": "Svalbard",
    "xs": "Illas Spratly",
    "xt": "Illa Tromelin",
    "xu": "At\u00f2l Johnston",
    "xv": "Illa Navassa",
    "xw": "Cisjordania",
    "ye": "Iem\u00e8n",
    "yt": "Mai\u00f2ta",
    "za": "Sud-Africa",
    "zm": "Zambia",
    "zw": "Zimbabwe"
}