{
    "af": "Afganistan",
    "za": "Africa de Sud",
    "qz": "Akrotiri",
    "al": "Albania",
    "dz": "Algeria",
    "ad": "Andora",
    "ao": "Angola",
    "ai": "Anguilla",
    "aq": "Antarctica",
    "ag": "Antigua \u0219i Barbuda",
    "sa": "Arabia Saudit\u0103",
    "ar": "Argentina",
    "am": "Armenia",
    "aw": "Aruba",
    "xu": "Atolul Johnston",
    "xl": "Atolul Palmyra",
    "au": "Australia",
    "at": "Austria",
    "az": "Azerbaijan",
    "bs": "Bahamas",
    "bh": "Bahrein",
    "bd": "Banglade\u0219",
    "bb": "Barbados",
    "qs": "Bassas da India",
    "by": "Belarus",
    "be": "Belgia",
    "bz": "Belize",
    "bj": "Benin",
    "bm": "Bermude",
    "mm": "Birmania",
    "bo": "Bolivia",
    "bq": "Bonaire, Sint Eustatius \u0219i Saba",
    "ba": "Bosnia \u0219i Her\u021begovina",
    "bw": "Botswana",
    "br": "Brazilia",
    "bn": "Brunei",
    "bg": "Bulgaria",
    "bf": "Burkina Faso",
    "bi": "Burundi",
    "bt": "Butan",
    "kh": "Cambodgia",
    "cm": "Camerun",
    "ca": "Canada",
    "cv": "Capul Verde",
    "cl": "Chile",
    "cn": "China",
    "td": "Ciad",
    "cy": "Cipru",
    "xw": "Cisiordania",
    "ci": "Coasta de Filde\u0219",
    "co": "Columbia",
    "km": "Comoros",
    "cg": "Congo (Brazzaville)",
    "cd": "Congo (Kinshasa)",
    "kp": "Coreea de Nord",
    "kr": "Coreea de Sud",
    "cr": "Costa Rica",
    "hr": "Croa\u021bia",
    "cu": "Cuba",
    "cw": "Cura\u00e7ao",
    "dk": "Danemarca",
    "xd": "Dhekelia",
    "dg": "Diego Garcia",
    "dj": "Djibuti",
    "dm": "Dominica",
    "ec": "Ecuador",
    "eg": "Egipt",
    "ch": "Elve\u021bia",
    "ae": "Emiratele Arabe Unite",
    "er": "Eritreea",
    "ee": "Estonia",
    "et": "Etiopia",
    "fj": "Fiji",
    "ph": "Filipine",
    "fi": "Finlanda",
    "fr": "Fran\u021ba",
    "xg": "F\u00e2\u0219ia Gaza",
    "ga": "Gabon",
    "gm": "Gambia",
    "ge": "Georgia",
    "gs": "Georgia de Sud \u0219i Insulele Sandwich de Sud",
    "de": "Germania",
    "gh": "Ghana",
    "gi": "Gibraltar",
    "gr": "Grecia",
    "gd": "Grenada",
    "gl": "Groenlanda",
    "gp": "Guadeloupe",
    "gu": "Guam",
    "gt": "Guatemala",
    "gg": "Guernsey",
    "gf": "Guiana Francez\u0103",
    "gq": "Guinea Ecuatorial\u0103",
    "gn": "Guineea",
    "gw": "Guineea-Bissau",
    "gy": "Guyana",
    "ht": "Haiti",
    "hn": "Honduras",
    "hk": "Hong Kong",
    "in": "India",
    "id": "Indonezia",
    "xb": "Insula Baker",
    "bv": "Insula Bouvet",
    "cp": "Insula Clipperton",
    "xe": "Insula Europa",
    "hm": "Insula Heard \u0219i Insulele McDonald",
    "xh": "Insula Howland",
    "xq": "Insula Jarvis",
    "qu": "Insula Juan de Nova",
    "im": "Insula Man",
    "xv": "Insula Navassa",
    "nf": "Insula Norfolk",
    "xt": "Insula Tromelin",
    "qw": "Insula Wake",
    "xa": "Insulele Ashmore \u0219i Cartier",
    "ky": "Insulele Cayman",
    "cx": "Insulele Christmas",
    "cc": "Insulele Cocos (Keeling)",
    "ck": "Insulele Cook",
    "fk": "Insulele Falkland (Malvine)",
    "fo": "Insulele Feroe",
    "qx": "Insulele Glorioso",
    "mp": "Insulele Mariana de Nord",
    "mh": "Insulele Marshall",
    "qm": "Insulele Midway",
    "xp": "Insulele Paracel",
    "pn": "Insulele Pitcairn",
    "sb": "Insulele Solomon",
    "xs": "Insulele Spratly",
    "tc": "Insulele Turks \u0219i Caicos",
    "vg": "Insulele Virgine, Britanice",
    "vi": "Insulele Virgine, Statele Unite",
    "xc": "Insulele din Marea Coralilor",
    "jo": "Iordania",
    "iq": "Irak",
    "ir": "Iran",
    "ie": "Irlanda",
    "is": "Islanda",
    "il": "Israel",
    "it": "Italia",
    "jm": "Jamaica",
    "xj": "Jan Mayen",
    "jp": "Japonia",
    "je": "Jersey",
    "kz": "Kazahstan",
    "ke": "Kenia",
    "ki": "Kiribati",
    "xk": "Kosovo",
    "kw": "Kuweit",
    "kg": "K\u00e2rg\u00e2zstan",
    "la": "Laos",
    "ls": "Lesoto",
    "lv": "Letonia",
    "lb": "Liban",
    "lr": "Liberia",
    "ly": "Libia",
    "li": "Liechtenstein",
    "lt": "Lituania",
    "lu": "Luxemburg",
    "mo": "Macao",
    "mk": "Macedonia",
    "mg": "Madagascar",
    "my": "Malaezia",
    "mw": "Malawi",
    "mv": "Maldive",
    "ml": "Mali",
    "mt": "Malta",
    "gb": "Marea Britanie",
    "ma": "Maroc",
    "mq": "Martinica",
    "mr": "Mauritania",
    "mu": "Mauritius",
    "yt": "Mayotte",
    "mx": "Mexic",
    "mc": "Monaco",
    "mn": "Mongolia",
    "ms": "Montserrat",
    "mz": "Mozambic",
    "me": "Muntenegru",
    "na": "Namibia",
    "nr": "Nauru",
    "np": "Nepal",
    "ni": "Nicaragua",
    "ne": "Niger",
    "ng": "Nigeria",
    "nu": "Niue",
    "no": "Norvegia",
    "nc": "Noua Caledonie",
    "nz": "Noua Zeeland\u0103",
    "nl": "Olanda",
    "om": "Oman",
    "va": "Ora\u0219ul Vatican",
    "pk": "Pakistan",
    "pw": "Palau",
    "pa": "Panama",
    "pg": "Papua Noua Guinee",
    "py": "Paraguay",
    "pe": "Peru",
    "pf": "Polinezia Francez\u0103",
    "pl": "Polonia",
    "pr": "Porto Rico",
    "pt": "Portugalia",
    "qa": "Qatar",
    "xm": "Reciful Kingman",
    "cf": "Republica Centrafrican\u0103",
    "do": "Republica Dominican\u0103",
    "md": "Republica Moldova",
    "cz": "Republica ceh\u0103",
    "re": "Reunion",
    "ro": "Rom\u00e2nia",
    "rw": "Ruanda",
    "ru": "Rusia",
    "eh": "Sahara de vest",
    "bl": "Saint Barthelemy",
    "kn": "Saint Kitts \u0219i Nevis",
    "pm": "Saint Pierre \u0219i Miquelon",
    "vc": "Saint Vincent \u0219i Grenadine",
    "sv": "Salvador",
    "ws": "Samoa",
    "as": "Samoa American\u0103",
    "sm": "San Marino",
    "lc": "Santa Lucia",
    "st": "Sao Tome \u0219i Principe",
    "sn": "Senegal",
    "rs": "Serbia",
    "sc": "Seychelles",
    "sh": "Sf\u00e2nta Elena, Ascension \u0219i Tristan da Cunha",
    "mf": "Sf\u00e2ntul Martin",
    "sx": "Sf\u00e2ntul Martin",
    "sl": "Sierra Leone",
    "sg": "Singapore",
    "sy": "Siria",
    "sk": "Slovacia",
    "si": "Slovenia",
    "so": "Somalia",
    "es": "Spania",
    "lk": "Sri Lanka",
    "us": "Statele Unite",
    "fm": "Statele federale ale Microneziei",
    "sz": "Suaziland",
    "sd": "Sudan",
    "ss": "Sudanul de Sud",
    "se": "Suedia",
    "sr": "Surinam",
    "xr": "Svalbard",
    "tw": "Taiwan",
    "tj": "Tajikistan",
    "tz": "Tanzania",
    "tf": "Teritoriile australe \u0219i antarctice franceze",
    "io": "Teritoriul britanic din Oceanul Indian",
    "th": "Thailanda",
    "tl": "Timorul de Est",
    "tg": "Togo",
    "tk": "Tokelau",
    "to": "Tonga",
    "tt": "Trinidad \u0219i Tobago",
    "tn": "Tunisia",
    "tr": "Turcia",
    "tm": "Turkmenistan",
    "tv": "Tuvalu",
    "ua": "Ucraina",
    "ug": "Uganda",
    "hu": "Ungaria",
    "uy": "Uruguay",
    "uz": "Uzbekistan",
    "vu": "Vanuatu",
    "ve": "Venezuela",
    "vn": "Vietnam",
    "wf": "Wallis \u0219i Futuna",
    "ye": "Yemen",
    "zm": "Zambia",
    "zw": "Zimbabwe"
}